{
  "video_id": "-cWi1fiL1E0",
  "video_title": "How To Make $10 MILLION from scratch",
  "summary_version": "1.0.0",
  "generated_at": "2025-10-17T07:08:43.273183",
  "content_profile": {
    "title": "How To Make $10 MILLION from scratch",
    "video_type": "entrepreneurship",
    "type_confidence": 0.334,
    "primary_themes": [],
    "experience_level": "advanced",
    "industry_focus": [
      "general"
    ],
    "content_density": 7,
    "category_distribution": {
      "products_tools": 2,
      "business_strategies": 2,
      "problems_solutions": 1,
      "startup_ideas": 1,
      "growth_tactics": 1,
      "ai_workflows": 0,
      "trends_signals": 1
    }
  },
  "key_takeaways": [
    "Solution: Gradually increase spending comfort levels (Difficulty: intermediate)",
    "Growth Tactic: Premium newsletter with community component (Channel: content)",
    "Strategy: Recurring revenue as foundation, not end goal",
    "Strategy: High-margin products enable affiliate marketing army",
    "Startup Opportunity: Pet AG1 - Premium pet supplement (Target: Affluent pet owners)"
  ],
  "standout_insights": [],
  "opportunity_map": {
    "total_opportunities": 3,
    "by_type": {
      "startup_ideas": 1,
      "market_gaps": 1,
      "trend_opportunities": 1
    },
    "opportunities": {
      "startup_ideas": [
        {
          "type": "startup_idea",
          "title": "Pet AG1 - Premium pet supplement",
          "target_market": "Affluent pet owners",
          "problem_solved": "Pet health and nutrition concerns",
          "business_model": "High-margin subscription supplement with affiliate marketing",
          "validation": "Even less proof needed than human supplements - pets can't provide feedback",
          "estimated_investment": "Partnership with water manufacturer for production and distribution"
        }
      ],
      "market_gaps": [
        {
          "type": "market_gap",
          "title": "Scaling spending habits with income growth",
          "solution_approach": "Gradually increase spending comfort levels",
          "difficulty": "intermediate",
          "tools_needed": [
            "mindset work",
            "financial planning"
          ]
        }
      ],
      "trend_opportunities": [
        {
          "type": "trend_opportunity",
          "title": "Premium pet supplements market opportunity",
          "stage": "early",
          "category": "market",
          "opportunity": "Apply successful human supplement model to pets with even less proof requirements"
        }
      ]
    }
  },
  "comment_intelligence": {
    "available": true,
    "total_comment_insights": 2,
    "total_validated_comments": 2,
    "total_comment_trends": 2,
    "insight_types": {
      "validation": 1,
      "feedback": 1
    },
    "top_high_engagement_comments": [],
    "comment_derived_trends": [
      {
        "trend": "Demand for collaborative business content",
        "supporting_comments": [
          "Should we make this a recurring monthly collab??",
          "Such a fun convo. Will do a Part 2!"
        ],
        "frequency": "2 high-engagement comments",
        "business_implication": "Collaborative content format drives higher engagement and audience retention"
      },
      {
        "trend": "Audience seeking mindset shifts around money and business",
        "supporting_comments": [
          "This is a mindset shift for me",
          "I spent a bunch of money on this - I feel great I love it"
        ],
        "frequency": "Multiple comments",
        "business_implication": "Market opportunity for content addressing psychology of wealth and spending"
      }
    ]
  },
  "metrics_summary": {
    "total_insights": 21,
    "high_value_insights": 1,
    "avg_actionability": 13.2,
    "avg_specificity": 16.8,
    "avg_evidence": 15.3,
    "avg_recency": 72.9
  },
  "practical_next_steps": [
    "Validate one of the startup ideas with target market interviews",
    "Review mistakes to avoid and create prevention checklist"
  ],
  "related_videos_keywords": [
    "general",
    "service",
    "supplement",
    "growth",
    "monetization"
  ]
}