{
  "video_id": "LrpVGDmRS9A",
  "video_title": "The ultimate guide to product building with the man who changed software",
  "summary_version": "1.0.0",
  "generated_at": "2025-10-17T07:08:43.284948",
  "content_profile": {
    "title": "The ultimate guide to product building with the man who changed software",
    "video_type": "market_research",
    "type_confidence": 0.311,
    "primary_themes": [],
    "experience_level": "advanced",
    "industry_focus": [
      "Mobile"
    ],
    "content_density": 7,
    "category_distribution": {
      "products_tools": 2,
      "business_strategies": 2,
      "problems_solutions": 1,
      "startup_ideas": 1,
      "growth_tactics": 1,
      "ai_workflows": 0,
      "trends_signals": 2
    }
  },
  "key_takeaways": [
    "Solution: Make ads the primary product that users seek out (Difficulty: intermediate)",
    "Growth Tactic: Create simple, shareable daily habit that spreads through word of mouth (Channel: viral)",
    "Strategy: Make advertising the product itself rather than an interruption",
    "Strategy: Daily habit formation through once-per-day app interaction",
    "Startup Opportunity: Daily scratch-off advertising app with reward mechanism (Target: Global mobile users seeking daily entertainment an)"
  ],
  "standout_insights": [],
  "opportunity_map": {
    "total_opportunities": 4,
    "by_type": {
      "startup_ideas": 1,
      "market_gaps": 1,
      "trend_opportunities": 2
    },
    "opportunities": {
      "startup_ideas": [
        {
          "type": "startup_idea",
          "title": "Daily scratch-off advertising app with reward mechanism",
          "target_market": "Global mobile users seeking daily entertainment and potential rewards",
          "problem_solved": "Making advertising engaging rather than intrusive",
          "business_model": "Advertising revenue from companies paying for scratch-off ad placements",
          "validation": "Build simple version and measure daily engagement",
          "estimated_investment": "Minimal - described as 'almost nothing to do to make this happen except getting the word out'"
        }
      ],
      "market_gaps": [
        {
          "type": "market_gap",
          "title": "Traditional ads are interruptions that users avoid",
          "solution_approach": "Make ads the primary product that users seek out",
          "difficulty": "intermediate",
          "tools_needed": [
            "mobile app development",
            "touch screen interaction",
            "microphone integration"
          ]
        }
      ],
      "trend_opportunities": [
        {
          "type": "trend_opportunity",
          "title": "Cozy software movement - making technology more playful and less serious",
          "stage": "early",
          "category": "technology",
          "opportunity": "Create more human, playful digital experiences"
        },
        {
          "type": "trend_opportunity",
          "title": "Making the internet weird again",
          "stage": "growing",
          "category": "consumer-behavior",
          "opportunity": "Develop unconventional, playful digital products"
        }
      ]
    }
  },
  "comment_intelligence": {
    "available": true,
    "total_comment_insights": 3,
    "total_validated_comments": 3,
    "total_comment_trends": 2,
    "insight_types": {
      "validation": 1,
      "feedback": 1,
      "trend": 1
    },
    "top_high_engagement_comments": [],
    "comment_derived_trends": [
      {
        "trend": "Appetite for playful, experimental software approaches",
        "supporting_comments": [
          "Thank you for sharing the idea of being playful, curious, and experimen",
          "This idea is BONKERS! Love it"
        ],
        "frequency": "Multiple comments",
        "business_implication": "Market opportunity for non-traditional, fun software experiences"
      },
      {
        "trend": "Skepticism balanced with interest in execution",
        "supporting_comments": [
          "1st idea literally everyone has thought of before",
          "Cool idea! 100 million might be a stretch"
        ],
        "frequency": "Several comments",
        "business_implication": "Ideas need strong execution and realistic expectations to succeed"
      }
    ]
  },
  "metrics_summary": {
    "total_insights": 25,
    "high_value_insights": 1,
    "avg_actionability": 12.4,
    "avg_specificity": 12.8,
    "avg_evidence": 14.4,
    "avg_recency": 72.6
  },
  "practical_next_steps": [
    "Validate one of the startup ideas with target market interviews",
    "Review mistakes to avoid and create prevention checklist"
  ],
  "related_videos_keywords": [
    "monetization",
    "mobile-app",
    "growth",
    "Mobile"
  ]
}