{
  "video_id": "QFR8aK9NUxw",
  "video_title": "Why a Gamer Mindset Can Change Your Life and Business with Nicolas Cole and Dickie Bush",
  "summary_version": "1.0.0",
  "generated_at": "2025-10-17T07:08:43.397595",
  "content_profile": {
    "title": "Why a Gamer Mindset Can Change Your Life and Business with Nicolas Cole and Dickie Bush",
    "video_type": "entrepreneurship",
    "type_confidence": 0.35,
    "primary_themes": [],
    "experience_level": "advanced",
    "industry_focus": [
      "general"
    ],
    "content_density": 7,
    "category_distribution": {
      "products_tools": 1,
      "business_strategies": 2,
      "problems_solutions": 1,
      "startup_ideas": 1,
      "growth_tactics": 1,
      "ai_workflows": 0,
      "trends_signals": 2
    }
  },
  "key_takeaways": [
    "Solution: Develop gamer mindset - treat business like video game grinding (Difficulty: intermediate)",
    "Growth Tactic: Consistent online writing to become discoverable (Channel: content)",
    "Strategy: Build audience through consistent online writing to explore opportunities",
    "Strategy: Online business as real-world video game with better rewards",
    "Startup Opportunity: Platform democratizing access to friendship through shared interests (Target: People with obsessive personalities who feel like )"
  ],
  "standout_insights": [],
  "opportunity_map": {
    "total_opportunities": 3,
    "by_type": {
      "startup_ideas": 1,
      "market_gaps": 1,
      "trend_opportunities": 1
    },
    "opportunities": {
      "startup_ideas": [
        {
          "type": "startup_idea",
          "title": "Platform democratizing access to friendship through shared interests",
          "target_market": "People with obsessive personalities who feel like odd ones out",
          "problem_solved": "Difficulty finding like-minded people with similar obsessions",
          "business_model": "not specified",
          "validation": "Internet already enabling this through writing platforms",
          "estimated_investment": "not mentioned"
        }
      ],
      "market_gaps": [
        {
          "type": "market_gap",
          "title": "Low threshold for pain and inability to do boring tasks consistently",
          "solution_approach": "Develop gamer mindset - treat business like video game grinding",
          "difficulty": "intermediate",
          "tools_needed": [
            "gaming experience or mindset training"
          ]
        }
      ],
      "trend_opportunities": [
        {
          "type": "trend_opportunity",
          "title": "Gaming backgrounds becoming common among successful entrepreneurs",
          "stage": "growing",
          "category": "market",
          "opportunity": "Leverage gaming skills for business success, target gamers for entrepreneurship education"
        }
      ]
    }
  },
  "comment_intelligence": {
    "available": true,
    "total_comment_insights": 1,
    "total_validated_comments": 1,
    "total_comment_trends": 1,
    "insight_types": {
      "validation": 1
    },
    "top_high_engagement_comments": [],
    "comment_derived_trends": [
      {
        "trend": "People stuck in analysis paralysis phase of starting",
        "supporting_comments": [
          "I'm the dude sitting in my room just thinking about starting"
        ],
        "frequency": "1 comment but likely represents larger segment",
        "business_implication": "Opportunity to create content and services specifically for people in the 'thinking about starting' phase"
      }
    ]
  },
  "metrics_summary": {
    "total_insights": 16,
    "high_value_insights": 1,
    "avg_actionability": 14.5,
    "avg_specificity": 15.0,
    "avg_evidence": 11.5,
    "avg_recency": 70.6
  },
  "practical_next_steps": [
    "Validate one of the startup ideas with target market interviews",
    "Review mistakes to avoid and create prevention checklist"
  ],
  "related_videos_keywords": [
    "monetization",
    "service",
    "growth",
    "general"
  ]
}